amiyautils/IOUtils.py
amiyautils/__init__.py
amiyautils/systemUtils.py
amiyautils/toolsUtils.py
amiyautils/urlUtils.py
amiyautils-0.0.2.dist-info/LICENSE
amiyautils-0.0.2.dist-info/METADATA
amiyautils-0.0.2.dist-info/WHEEL
amiyautils-0.0.2.dist-info/top_level.txt
amiyautils-0.0.2.dist-info/RECORD
