Metadata-Version: 2.1
Name: amiyautils
Version: 0.0.2
Summary: 一个简单的实用工具库
Home-page: https://github.com/AmiyaBot/Amiya-Utils
Author: vivien8261
Author-email: 826197021@qq.com
License: MIT Licence
Requires-Python: >=3.10
License-File: LICENSE
Requires-Dist: requests~=2.32.4
Requires-Dist: zhon~=2.1.1
